{"stats":{"minecraft:custom":{"minecraft:time_since_rest":644,"minecraft:crouch_one_cm":75,"minecraft:play_one_minute":6370,"minecraft:deaths":1,"minecraft:sprint_one_cm":21696,"minecraft:damage_taken":220,"minecraft:walk_one_cm":8956,"minecraft:sneak_time":75,"minecraft:mob_kills":3,"minecraft:jump":168,"minecraft:damage_dealt":240,"minecraft:leave_game":3,"minecraft:time_since_death":606,"minecraft:fall_one_cm":8381,"minecraft:fly_one_cm":22443},"minecraft:mined":{"minecraft:grass":1,"minecraft:oak_log":1,"minecraft:oak_leaves":5},"minecraft:picked_up":{"minecraft:wooden_axe":1,"minecraft:oak_log":12,"minecraft:oak_sapling":6,"minecraft:mutton":8,"minecraft:white_wool":6},"minecraft:killed":{"minecraft:sheep":3},"minecraft:used":{"minecraft:wooden_axe":9}},"DataVersion":2586}